{
    "myIntents": [
        {
            "dataType": null, 
            "consumerMethod": "startService", 
            "action": "com.evernote.action.SAVE_NOTEBOOK", 
            "sender": "com.evernote.ui.NotebookFragment"
        }, 
        {
            "dataType": null, 
            "consumerMethod": "startActivity", 
            "action": null, 
            "sender": "com.evernote.billing.u"
        }, 
        {
            "dataType": null, 
            "consumerMethod": "startService", 
            "action": "com.evernote.action.RESET_PASSWORD", 
            "sender": "com.evernote.ui.ResetPasswordFragment"
        }, 
        {
            "dataType": null, 
            "consumerMethod": "startService", 
            "action": "com.evernote.action.SAVE_STACK", 
            "sender": "com.evernote.ui.NotebookFragment"
        }, 
        {
            "dataType": null, 
            "consumerMethod": "sendBroadcast", 
            "action": "com.evernote.action.QUOTA_STATUS", 
            "sender": "com.evernote.client.SyncService"
        }, 
        {
            "dataType": null, 
            "consumerMethod": "startService", 
            "action": null, 
            "sender": "com.evernote.provider.EvernoteProvider"
        }, 
        {
            "dataType": null, 
            "consumerMethod": "setResult", 
            "action": null, 
            "sender": "com.evernote.ui.NewNoteActivity"
        }, 
        {
            "dataType": null, 
            "consumerMethod": "sendOrderedBroadcast", 
            "action": "com.evernote.action.LOG_IN_PREP_DONE", 
            "sender": "com.evernote.client.EvernoteService"
        }, 
        {
            "dataType": null, 
            "consumerMethod": "startActivity", 
            "action": null, 
            "sender": "com.evernote.ui.ResetPasswordFragment"
        }, 
        {
            "dataType": null, 
            "consumerMethod": "sendOrderedBroadcast", 
            "action": null, 
            "sender": "com.evernote.util.an"
        }, 
        {
            "dataType": null, 
            "consumerMethod": "sendBroadcast", 
            "action": "com.evernote.SD_CARD_STILL_MOUNTED", 
            "sender": "com.evernote.provider.ac"
        }, 
        {
            "dataType": null, 
            "consumerMethod": "startActivity", 
            "action": null, 
            "sender": "com.evernote.ui.helper.dg"
        }, 
        {
            "dataType": null, 
            "consumerMethod": "setIntent", 
            "action": null, 
            "sender": "com.evernote.ui.RegistrationFragment"
        }, 
        {
            "dataType": null, 
            "consumerMethod": "startActivity", 
            "action": null, 
            "sender": "com.evernote.billing.BillingActivity"
        }, 
        {
            "dataType": null, 
            "consumerMethod": "startService", 
            "action": "com.evernote.action.LOG_IN", 
            "sender": "com.evernote.ui.LoginFragment"
        }, 
        {
            "dataType": null, 
            "consumerMethod": "setResult", 
            "action": null, 
            "sender": "com.evernote.ui.TagEditActivity"
        }, 
        {
            "dataType": null, 
            "consumerMethod": "startActivity", 
            "action": null, 
            "sender": "com.evernote.util.ah"
        }, 
        {
            "dataType": null, 
            "consumerMethod": "startService", 
            "action": "com.evernote.action.UPDATE_NOTE_TAGS", 
            "sender": "com.evernote.ui.TagEditActivity"
        }, 
        {
            "dataType": null, 
            "consumerMethod": "startService", 
            "action": "com.evernote.action.EXPORT_RESOURCES", 
            "sender": "com.evernote.ui.NoteViewFragment"
        }, 
        {
            "dataType": null, 
            "consumerMethod": "startService", 
            "action": null, 
            "sender": "com.evernote.ui.os"
        }, 
        {
            "dataType": null, 
            "consumerMethod": "startActivity", 
            "action": null, 
            "sender": "com.evernote.ui.qa"
        }, 
        {
            "dataType": null, 
            "consumerMethod": "startService", 
            "action": "com.evernote.action.CLEAN_SHARE_DIR", 
            "sender": "com.evernote.client.SyncService"
        }, 
        {
            "dataType": null, 
            "consumerMethod": "bindService", 
            "action": "com.android.vending.billing.MarketBillingService.BIND", 
            "sender": "com.evernote.billing.BillingService"
        }, 
        {
            "dataType": null, 
            "consumerMethod": "startActivityForResult", 
            "action": null, 
            "sender": "com.evernote.ui.pinlock.LockablePreferenceActivity"
        }, 
        {
            "dataType": null, 
            "consumerMethod": "startActivityForResult", 
            "action": null, 
            "sender": "com.evernote.ui.RegistrationFragment"
        }, 
        {
            "dataType": null, 
            "consumerMethod": "startActivity", 
            "action": null, 
            "sender": "com.evernote.ui.og"
        }, 
        {
            "dataType": null, 
            "consumerMethod": "startService", 
            "action": "com.evernote.action.LOG_IN", 
            "sender": "com.evernote.ui.CaptchaFragment"
        }, 
        {
            "dataType": null, 
            "consumerMethod": "setResult", 
            "action": null, 
            "sender": "com.evernote.ui.NoteListFragment"
        }, 
        {
            "dataType": null, 
            "consumerMethod": "sendBroadcast", 
            "action": "com.android.launcher.action.INSTALL_SHORTCUT", 
            "sender": "com.evernote.ui.NoteViewFragment"
        }, 
        {
            "dataType": null, 
            "consumerMethod": "sendOrderedBroadcast", 
            "action": "com.evernote.action.SYNC_ERROR", 
            "sender": "com.evernote.provider.EvernoteProvider"
        }, 
        {
            "dataType": null, 
            "consumerMethod": "startActivity", 
            "action": "hasValue", 
            "sender": "com.evernote.ui.SDCardChangedActivity"
        }, 
        {
            "dataType": null, 
            "consumerMethod": "startActivity", 
            "action": null, 
            "sender": "com.evernote.ui.pinlock.LockableEvernoteFragementActivity"
        }, 
        {
            "dataType": null, 
            "consumerMethod": "startService", 
            "action": "com.evernote.action.LOG_OUT", 
            "sender": "com.evernote.ui.of"
        }, 
        {
            "dataType": null, 
            "consumerMethod": "startActivity", 
            "action": null, 
            "sender": "com.evernote.ui.TabManager"
        }, 
        {
            "dataType": null, 
            "consumerMethod": "startActivity", 
            "action": null, 
            "sender": "com.evernote.ui.helper.StopAudioNoteReceiver"
        }, 
        {
            "dataType": null, 
            "consumerMethod": "startActivity", 
            "action": null, 
            "sender": "com.evernote.ui.ac"
        }, 
        {
            "dataType": null, 
            "consumerMethod": "startService", 
            "action": "com.evernote.action.FULL_SYNC", 
            "sender": "com.evernote.ui.NotebookFragment"
        }, 
        {
            "dataType": "\"application/zip\"", 
            "consumerMethod": "startActivity", 
            "action": null, 
            "sender": "com.evernote.util.SendLogTask"
        }, 
        {
            "dataType": null, 
            "consumerMethod": "startActivity", 
            "action": null, 
            "sender": "com.evernote.ui.pinlock.a"
        }, 
        {
            "dataType": null, 
            "consumerMethod": "startService", 
            "action": "com.evernote.action.GET_CAPTCHA", 
            "sender": "com.evernote.ui.CaptchaFragment"
        }, 
        {
            "dataType": null, 
            "consumerMethod": "startActivity", 
            "action": "com.evernote.action.DUMMY_ACTION", 
            "sender": "com.evernote.ui.HomeFragment"
        }, 
        {
            "dataType": null, 
            "consumerMethod": "sendOrderedBroadcast", 
            "action": "com.evernote.action.LOGOUT_DONE", 
            "sender": "com.evernote.client.EvernoteService"
        }, 
        {
            "dataType": null, 
            "consumerMethod": "sendOrderedBroadcast", 
            "action": "com.evernote.action.THUMBNAIL_DONE", 
            "sender": "com.evernote.util.an"
        }, 
        {
            "dataType": null, 
            "consumerMethod": "startActivity", 
            "action": "ACTION_LINK_NOTEBOOK", 
            "sender": "com.evernote.ui.helper.URIBrokerActivity"
        }, 
        {
            "dataType": null, 
            "consumerMethod": "sendBroadcast", 
            "action": "com.evernote.action.ACTION_PIN_SHOW_WIDGET_CHANGED", 
            "sender": "com.evernote.ui.ph"
        }, 
        {
            "dataType": null, 
            "consumerMethod": "startActivity", 
            "action": null, 
            "sender": "com.evernote.ui.LoginFragment"
        }, 
        {
            "dataType": null, 
            "consumerMethod": "sendOrderedBroadcast", 
            "action": "com.evernote.action.SAVE_NOTE_DONE", 
            "sender": "com.evernote.client.EvernoteService"
        }, 
        {
            "dataType": null, 
            "consumerMethod": "sendBroadcast", 
            "action": "com.evernote.action.ACTION_PINLOCK_STATE_CHANGE", 
            "sender": "com.evernote.ui.pinlock.b"
        }, 
        {
            "dataType": null, 
            "consumerMethod": "startService", 
            "action": "com.evernote.action.MOVE_NOTE", 
            "sender": "com.evernote.ui.NoteListFragment"
        }, 
        {
            "dataType": null, 
            "consumerMethod": "startService", 
            "action": "com.evernote.action.EXPORT_RESOURCES", 
            "sender": "com.evernote.ui.kq"
        }, 
        {
            "dataType": null, 
            "consumerMethod": "sendOrderedBroadcast", 
            "action": null, 
            "sender": "com.evernote.client.EvernoteService"
        }, 
        {
            "dataType": null, 
            "consumerMethod": "startService", 
            "action": "com.evernote.action.LOG_IN", 
            "sender": "com.evernote.ui.RegistrationFragment"
        }, 
        {
            "dataType": null, 
            "consumerMethod": "startActivity", 
            "action": "com.evernote.action.DUMMY_ACTION", 
            "sender": "com.evernote.ui.HomeActivity"
        }, 
        {
            "dataType": null, 
            "consumerMethod": "sendOrderedBroadcast", 
            "action": "com.evernote.ACTION_STOP_AUDIO_NOTE", 
            "sender": "com.evernote.ui.helper.LiveKeyAudioNoteReceiver"
        }, 
        {
            "dataType": null, 
            "consumerMethod": "sendOrderedBroadcast", 
            "action": "com.evernote.action.SYNC_DONE", 
            "sender": "com.evernote.client.SyncService"
        }, 
        {
            "dataType": null, 
            "consumerMethod": "sendBroadcast", 
            "action": null, 
            "sender": "com.evernote.ui.helper.by"
        }, 
        {
            "dataType": null, 
            "consumerMethod": "startService", 
            "action": "com.android.vending.billing.PURCHASE_STATE_CHANGED", 
            "sender": "com.evernote.billing.BillingReceiver"
        }, 
        {
            "dataType": null, 
            "consumerMethod": "sendBroadcast", 
            "action": "com.android.launcher.action.INSTALL_SHORTCUT", 
            "sender": "com.evernote.ui.jc"
        }, 
        {
            "dataType": null, 
            "consumerMethod": "setIntent", 
            "action": null, 
            "sender": "com.evernote.ui.maps.NoteListActivity"
        }, 
        {
            "dataType": null, 
            "consumerMethod": "startService", 
            "action": "com.evernote.action.FULL_SYNC", 
            "sender": "com.evernote.ui.EvernoteFragmentActivity"
        }, 
        {
            "dataType": null, 
            "consumerMethod": "startActivity", 
            "action": null, 
            "sender": "com.evernote.ui.pinlock.LockablePreferenceActivity"
        }, 
        {
            "dataType": null, 
            "consumerMethod": "startService", 
            "action": "com.evernote.action.LOG_OUT", 
            "sender": "com.evernote.ui.z"
        }, 
        {
            "dataType": null, 
            "consumerMethod": "startService", 
            "action": "com.evernote.action.SAVE_NOTE", 
            "sender": "com.evernote.client.Draft"
        }, 
        {
            "dataType": null, 
            "consumerMethod": "startActivity", 
            "action": null, 
            "sender": "com.evernote.ui.CaptchaFragment"
        }, 
        {
            "dataType": null, 
            "consumerMethod": "startService", 
            "action": "com.evernote.action.FULL_SYNC", 
            "sender": "com.evernote.ui.EvernotePreferenceActivity"
        }, 
        {
            "dataType": null, 
            "consumerMethod": "startService", 
            "action": "com.evernote.action.FULL_SYNC", 
            "sender": "com.evernote.provider.EvernoteProvider"
        }, 
        {
            "dataType": null, 
            "consumerMethod": "setIntent", 
            "action": null, 
            "sender": "com.evernote.ui.LoginFragment"
        }, 
        {
            "dataType": null, 
            "consumerMethod": "startService", 
            "action": "com.evernote.action.GET_REGISTRATION_URLS", 
            "sender": "com.evernote.ui.LoginFragment"
        }, 
        {
            "dataType": null, 
            "consumerMethod": "startService", 
            "action": "com.evernote.action.FULL_SYNC", 
            "sender": "com.evernote.ui.EvernoteStatusBar"
        }, 
        {
            "dataType": null, 
            "consumerMethod": "sendOrderedBroadcast", 
            "action": "com.evernote.action.SYNC_ERROR", 
            "sender": "com.evernote.client.SyncService"
        }, 
        {
            "dataType": null, 
            "consumerMethod": "startService", 
            "action": "com.evernote.action.LOG_OUT", 
            "sender": "com.evernote.ui.cj"
        }, 
        {
            "dataType": null, 
            "consumerMethod": "startActivity", 
            "action": null, 
            "sender": "com.evernote.ui.maps.r"
        }, 
        {
            "dataType": null, 
            "consumerMethod": "sendBroadcast", 
            "action": "com.evernote.action.LOG_IN", 
            "sender": "com.evernote.provider.q"
        }, 
        {
            "dataType": null, 
            "consumerMethod": "startService", 
            "action": "com.evernote.action.FULL_SYNC", 
            "sender": "com.evernote.billing.ah"
        }, 
        {
            "dataType": null, 
            "consumerMethod": "startService", 
            "action": "com.evernote.action.LOG_IN_PREP", 
            "sender": "com.evernote.ui.LoginFragment"
        }, 
        {
            "dataType": null, 
            "consumerMethod": "startActivity", 
            "action": null, 
            "sender": "com.evernote.ui.NotebookFragment"
        }, 
        {
            "dataType": null, 
            "consumerMethod": "startActivity", 
            "action": "com.evernote.action.DUMMY_ACTION", 
            "sender": "com.evernote.ui.de"
        }, 
        {
            "dataType": null, 
            "consumerMethod": "startService", 
            "action": "com.evernote.action.FULL_SYNC", 
            "sender": "com.evernote.ui.NewNoteActivity"
        }, 
        {
            "dataType": null, 
            "consumerMethod": "startService", 
            "action": "com.evernote.action.REGISTER", 
            "sender": "com.evernote.ui.CaptchaFragment"
        }, 
        {
            "dataType": null, 
            "consumerMethod": "sendOrderedBroadcast", 
            "action": "com.evernote.action.CHUNK_STARTED", 
            "sender": "com.evernote.client.SyncService"
        }, 
        {
            "dataType": null, 
            "consumerMethod": "sendBroadcast", 
            "action": "com.evernote.action.RESET_PASSWORD_RESULT", 
            "sender": "com.evernote.client.EvernoteService"
        }, 
        {
            "dataType": null, 
            "consumerMethod": "startService", 
            "action": "com.evernote.action.FULL_SYNC", 
            "sender": "com.evernote.ui.jx"
        }, 
        {
            "dataType": null, 
            "consumerMethod": "setResult", 
            "action": null, 
            "sender": "com.evernote.ui.CaptchaFragment"
        }, 
        {
            "dataType": null, 
            "consumerMethod": "startService", 
            "action": null, 
            "sender": "com.evernote.ui.EvernoteWidgetWSnippetProvider"
        }, 
        {
            "dataType": null, 
            "consumerMethod": "startService", 
            "action": "com.evernote.action.SAVE_STACK", 
            "sender": "com.evernote.ui.lg"
        }, 
        {
            "dataType": null, 
            "consumerMethod": "startService", 
            "action": "com.evernote.action.SAVE_TODO", 
            "sender": "com.evernote.ui.NoteViewFragment"
        }, 
        {
            "dataType": null, 
            "consumerMethod": "sendOrderedBroadcast", 
            "action": "com.evernote.action.CHUNK_DONE", 
            "sender": "com.evernote.client.SyncService"
        }, 
        {
            "dataType": null, 
            "consumerMethod": "startActivity", 
            "action": null, 
            "sender": "com.evernote.ui.maps.q"
        }, 
        {
            "dataType": null, 
            "consumerMethod": "startService", 
            "action": "com.evernote.action.FULL_SYNC", 
            "sender": "com.evernote.ui.LinkedNotebookFragment"
        }, 
        {
            "dataType": null, 
            "consumerMethod": "sendOrderedBroadcast", 
            "action": null, 
            "sender": "com.evernote.ui.helper.bq"
        }, 
        {
            "dataType": null, 
            "consumerMethod": "sendBroadcast", 
            "action": "com.evernote.action.SDCARD_CHANGED", 
            "sender": "com.evernote.provider.b"
        }, 
        {
            "dataType": null, 
            "consumerMethod": "startService", 
            "action": "com.evernote.action.GET_REGISTRATION_URLS", 
            "sender": "com.evernote.ui.CaptchaFragment"
        }, 
        {
            "dataType": null, 
            "consumerMethod": "sendBroadcast", 
            "action": "com.evernote.action.SYNC_ERROR", 
            "sender": "com.evernote.provider.EvernoteProvider"
        }, 
        {
            "dataType": null, 
            "consumerMethod": "sendBroadcast", 
            "action": "com.evernote.action.GET_CAPTCHA_RESULT", 
            "sender": "com.evernote.client.EvernoteService"
        }, 
        {
            "dataType": null, 
            "consumerMethod": "startService", 
            "action": null, 
            "sender": "com.evernote.ui.helper.WidgetUpdateReceiver"
        }, 
        {
            "dataType": null, 
            "consumerMethod": "startActivity", 
            "action": null, 
            "sender": "com.evernote.ui.helper.j"
        }, 
        {
            "dataType": null, 
            "consumerMethod": "setResult", 
            "action": null, 
            "sender": "com.evernote.ui.FilePickerActivity"
        }, 
        {
            "dataType": null, 
            "consumerMethod": "startService", 
            "action": "com.evernote.action.FULL_SYNC", 
            "sender": "com.evernote.client.EvernoteService"
        }, 
        {
            "dataType": null, 
            "consumerMethod": "sendBroadcast", 
            "action": "com.evernote.action.DB_CORRUPTED", 
            "sender": "com.evernote.provider.b"
        }, 
        {
            "dataType": null, 
            "consumerMethod": "startService", 
            "action": "com.evernote.action.CHECK_USERNAME", 
            "sender": "com.evernote.ui.RegistrationFragment"
        }, 
        {
            "dataType": null, 
            "consumerMethod": "startService", 
            "action": "com.evernote.action.FULL_SYNC", 
            "sender": "com.evernote.ui.helper.dg"
        }, 
        {
            "dataType": null, 
            "consumerMethod": "setIntent", 
            "action": null, 
            "sender": "com.evernote.ui.no"
        }, 
        {
            "dataType": null, 
            "consumerMethod": "startActivity", 
            "action": null, 
            "sender": "com.evernote.ui.RegistrationFragment"
        }, 
        {
            "dataType": null, 
            "consumerMethod": "startService", 
            "action": "com.evernote.action.REGISTER", 
            "sender": "com.evernote.ui.RegistrationFragment"
        }, 
        {
            "dataType": null, 
            "consumerMethod": "startService", 
            "action": "com.android.vending.billing.RESPONSE_CODE", 
            "sender": "com.evernote.billing.BillingReceiver"
        }, 
        {
            "dataType": null, 
            "consumerMethod": "sendBroadcast", 
            "action": "com.evernote.action.ACTION_RECENT_NOTES_CHANGED", 
            "sender": "com.evernote.provider.i"
        }, 
        {
            "dataType": null, 
            "consumerMethod": "sendBroadcast", 
            "action": null, 
            "sender": "com.evernote.provider.EvernoteProvider"
        }, 
        {
            "dataType": null, 
            "consumerMethod": "startService", 
            "action": "com.evernote.action.FULL_SYNC", 
            "sender": "com.evernote.ui.OfflineNotebookSettingsFragment"
        }, 
        {
            "dataType": null, 
            "consumerMethod": "sendOrderedBroadcast", 
            "action": "com.evernote.action.NOTE_DELETED", 
            "sender": "com.evernote.client.SyncService"
        }, 
        {
            "dataType": null, 
            "consumerMethod": "setIntent", 
            "action": null, 
            "sender": "com.evernote.ui.TabletFragmentActivity"
        }, 
        {
            "dataType": null, 
            "consumerMethod": "startService", 
            "action": "com.evernote.action.LOG_OUT", 
            "sender": "com.evernote.ui.ee"
        }, 
        {
            "dataType": null, 
            "consumerMethod": "startService", 
            "action": "com.evernote.action.LOG_IN", 
            "sender": "com.evernote.ui.AuthenticationActivity"
        }, 
        {
            "dataType": null, 
            "consumerMethod": "sendOrderedBroadcast", 
            "action": "com.evernote.action.CONTENT_DONE", 
            "sender": "com.evernote.provider.EvernoteProvider"
        }, 
        {
            "dataType": null, 
            "consumerMethod": "startService", 
            "action": "com.evernote.action.LOG_OUT", 
            "sender": "com.evernote.ui.qq"
        }, 
        {
            "dataType": null, 
            "consumerMethod": "startActivity", 
            "action": null, 
            "sender": "com.evernote.ui.ea"
        }, 
        {
            "dataType": null, 
            "consumerMethod": "startActivity", 
            "action": null, 
            "sender": "com.evernote.ui.cb"
        }, 
        {
            "dataType": null, 
            "consumerMethod": "startService", 
            "action": "com.evernote.action.RECOVER_NOTE", 
            "sender": "com.evernote.client.SyncService"
        }, 
        {
            "dataType": null, 
            "consumerMethod": "startService", 
            "action": "com.evernote.action.STOP_SEARCH_INDEXING", 
            "sender": "com.evernote.ui.helper.SyncNotification"
        }, 
        {
            "dataType": null, 
            "consumerMethod": "sendBroadcast", 
            "action": "android.intent.action.MEDIA_SCANNER_SCAN_FILE", 
            "sender": "com.evernote.client.EvernoteService"
        }, 
        {
            "dataType": null, 
            "consumerMethod": "startService", 
            "action": "com.evernote.action.GET_REGISTRATION_URLS", 
            "sender": "com.evernote.ui.RegistrationFragment"
        }, 
        {
            "dataType": null, 
            "consumerMethod": "startService", 
            "action": null, 
            "sender": "com.evernote.ui.SDCardChangedActivity"
        }, 
        {
            "dataType": null, 
            "consumerMethod": "startService", 
            "action": "com.evernote.action.CLEAR_HTML", 
            "sender": "com.evernote.provider.b"
        }, 
        {
            "dataType": null, 
            "consumerMethod": "sendOrderedBroadcast", 
            "action": "com.evernote.action.TAG_UPLOADED", 
            "sender": "com.evernote.client.SyncService"
        }, 
        {
            "dataType": null, 
            "consumerMethod": "startActivity", 
            "action": null, 
            "sender": "com.evernote.ui.by"
        }, 
        {
            "dataType": null, 
            "consumerMethod": "startService", 
            "action": "com.evernote.action.FULL_SYNC", 
            "sender": "com.evernote.ui.ex"
        }, 
        {
            "dataType": null, 
            "consumerMethod": "sendBroadcast", 
            "action": "com.evernote.action.GET_REGISTRATION_URLS_RESULT", 
            "sender": "com.evernote.client.EvernoteService"
        }, 
        {
            "dataType": null, 
            "consumerMethod": "setResult", 
            "action": null, 
            "sender": "com.evernote.ui.ju"
        }, 
        {
            "dataType": null, 
            "consumerMethod": "sendBroadcast", 
            "action": "com.android.launcher.action.INSTALL_SHORTCUT", 
            "sender": "com.evernote.ui.NoteListFragment"
        }, 
        {
            "dataType": null, 
            "consumerMethod": "startService", 
            "action": "com.evernote.action.FULL_SYNC", 
            "sender": "com.evernote.billing.ai"
        }, 
        {
            "dataType": null, 
            "consumerMethod": "startService", 
            "action": "com.evernote.action.FULL_SYNC", 
            "sender": "com.evernote.ui.EvernoteActivity"
        }, 
        {
            "dataType": null, 
            "consumerMethod": "startActivity", 
            "action": null, 
            "sender": "com.evernote.ui.EvernoteFragmentActivity"
        }, 
        {
            "dataType": null, 
            "consumerMethod": "sendBroadcast", 
            "action": "com.evernote.SD_CARD_STILL_MOUNTED", 
            "sender": "com.evernote.provider.aa"
        }, 
        {
            "dataType": null, 
            "consumerMethod": "startActivity", 
            "action": null, 
            "sender": "com.evernote.ui.helper.ShareUtils"
        }, 
        {
            "dataType": null, 
            "consumerMethod": "sendBroadcast", 
            "action": "com.evernote.action.CHECK_USERNAME_RESULT", 
            "sender": "com.evernote.client.EvernoteService"
        }, 
        {
            "dataType": null, 
            "consumerMethod": "sendBroadcast", 
            "action": "com.evernote.action.DB_READ_ONLY", 
            "sender": "com.evernote.provider.b"
        }, 
        {
            "dataType": null, 
            "consumerMethod": "sendOrderedBroadcast", 
            "action": "com.evernote.action.SYNC_STARTED", 
            "sender": "com.evernote.client.SyncService"
        }, 
        {
            "dataType": null, 
            "consumerMethod": "sendBroadcast", 
            "action": "com.evernote.action.DB_OPEN_CREATION_FAILED", 
            "sender": "com.evernote.provider.b"
        }, 
        {
            "dataType": null, 
            "consumerMethod": "sendOrderedBroadcast", 
            "action": "com.evernote.action.METADATA_DONE", 
            "sender": "com.evernote.client.SyncService"
        }, 
        {
            "dataType": null, 
            "consumerMethod": "startActivityForResult", 
            "action": null, 
            "sender": "com.evernote.ui.pinlock.LockableActivity"
        }, 
        {
            "dataType": null, 
            "consumerMethod": "startService", 
            "action": "com.evernote.action.START_SEARCH_INDEXING", 
            "sender": "com.evernote.ui.EvernotePreferenceActivity"
        }, 
        {
            "dataType": null, 
            "consumerMethod": "startActivity", 
            "action": "android.intent.action.VIEW", 
            "sender": "com.evernote.billing.f"
        }, 
        {
            "dataType": null, 
            "consumerMethod": "startActivity", 
            "action": null, 
            "sender": "com.evernote.ui.DYNDialogActivity"
        }, 
        {
            "dataType": null, 
            "consumerMethod": "startService", 
            "action": "com.evernote.action.FULL_SYNC", 
            "sender": "com.evernote.ui.mp"
        }, 
        {
            "dataType": null, 
            "consumerMethod": "startService", 
            "action": "com.evernote.action.CLEAR_CACHE", 
            "sender": "com.evernote.ui.EvernotePreferenceActivity"
        }, 
        {
            "dataType": null, 
            "consumerMethod": "startService", 
            "action": "com.evernote.action.START_SEARCH_INDEXING", 
            "sender": "com.evernote.ui.helper.SyncNotification"
        }, 
        {
            "dataType": null, 
            "consumerMethod": "startService", 
            "action": "com.evernote.action.FULL_SYNC", 
            "sender": "com.evernote.util.af"
        }, 
        {
            "dataType": null, 
            "consumerMethod": "startService", 
            "action": "com.evernote.action.FULL_SYNC", 
            "sender": "com.evernote.ui.helper.bq"
        }, 
        {
            "dataType": null, 
            "consumerMethod": "startService", 
            "action": "com.evernote.action.FULL_SYNC", 
            "sender": "com.evernote.provider.b"
        }, 
        {
            "dataType": null, 
            "consumerMethod": "startActivity", 
            "action": null, 
            "sender": "com.evernote.ui.NoteListFragment"
        }, 
        {
            "dataType": null, 
            "consumerMethod": "startActivity", 
            "action": null, 
            "sender": "com.evernote.ui.pinlock.LockableActivity"
        }, 
        {
            "dataType": null, 
            "consumerMethod": "sendOrderedBroadcast", 
            "action": "com.evernote.action.CONTENT_DONE", 
            "sender": "com.evernote.client.SyncService"
        }, 
        {
            "dataType": null, 
            "consumerMethod": "setResult", 
            "action": null, 
            "sender": "com.evernote.ui.EvernoteFragmentActivity"
        }, 
        {
            "dataType": null, 
            "consumerMethod": "startActivityForResult", 
            "action": null, 
            "sender": "com.evernote.ui.helper.dg"
        }, 
        {
            "dataType": null, 
            "consumerMethod": "startActivity", 
            "action": null, 
            "sender": "com.evernote.ui.StandardDialogActivity"
        }, 
        {
            "dataType": null, 
            "consumerMethod": "sendOrderedBroadcast", 
            "action": "com.evernote.action.RESOURCE_DONE", 
            "sender": "com.evernote.client.SyncService"
        }, 
        {
            "dataType": null, 
            "consumerMethod": "startService", 
            "action": null, 
            "sender": "com.evernote.ui.SearchActivity"
        }, 
        {
            "dataType": null, 
            "consumerMethod": "sendOrderedBroadcast", 
            "action": "com.evernote.action.NOTE_UPLOADED", 
            "sender": "com.evernote.client.SyncService"
        }, 
        {
            "dataType": null, 
            "consumerMethod": "startService", 
            "action": "com.evernote.billing.GET_PURCHASE_INFORMATION", 
            "sender": "com.evernote.billing.BillingReceiver"
        }, 
        {
            "dataType": null, 
            "consumerMethod": "sendBroadcast", 
            "action": "com.evernote.action.REGISTER_RESULT", 
            "sender": "com.evernote.client.EvernoteService"
        }, 
        {
            "dataType": null, 
            "consumerMethod": "startService", 
            "action": "com.evernote.action.FULL_SYNC", 
            "sender": "com.evernote.ui.rx"
        }, 
        {
            "dataType": null, 
            "consumerMethod": "sendOrderedBroadcast", 
            "action": "com.evernote.action.THUMBNAIL_DONE", 
            "sender": "com.evernote.client.SyncService"
        }, 
        {
            "dataType": null, 
            "consumerMethod": "sendBroadcast", 
            "action": "com.evernote.action.LOGIN_RESULT", 
            "sender": "com.evernote.client.EvernoteService"
        }
    ], 
    "packageName": "com.evernote", 
    "myComponents": [
        {
            "filter": [
                {
                    "data": [], 
                    "categories": [
                        "android.intent.category.LAUNCHER", 
                        "android.intent.category.DEFAULT"
                    ], 
                    "actions": [
                        "android.intent.action.MAIN"
                    ]
                }
            ], 
            "type": "activity", 
            "name": "ui.HomeActivity"
        }, 
        {
            "filter": [], 
            "type": "activity", 
            "name": "ui.PhoneMainActivity"
        }, 
        {
            "filter": [], 
            "type": "activity", 
            "name": "com.evernote.ui.TabletFragmentActivity"
        }, 
        {
            "filter": [], 
            "type": "activity", 
            "name": "com.evernote.ui.maps.EvernoteMapActivity"
        }, 
        {
            "filter": [], 
            "type": "activity", 
            "name": "com.evernote.ui.maps.SnippetActivity"
        }, 
        {
            "filter": [], 
            "type": "activity", 
            "name": "com.evernote.ui.maps.NoteListActivity"
        }, 
        {
            "filter": [], 
            "type": "activity", 
            "name": "com.evernote.ui.maps.MapActivityGroup"
        }, 
        {
            "filter": [], 
            "type": "activity", 
            "name": "com.evernote.ui.maps.PinDropActivity"
        }, 
        {
            "filter": [], 
            "type": "activity", 
            "name": "com.evernote.ui.PinLockActivity"
        }, 
        {
            "filter": [
                {
                    "data": [], 
                    "categories": [
                        "android.intent.category.DEFAULT"
                    ], 
                    "actions": [
                        "com.evernote.action.SECURITY_PREFERENCES"
                    ]
                }
            ], 
            "type": "activity", 
            "name": "com.evernote.ui.SecurityPreferenceActivity"
        }, 
        {
            "filter": [], 
            "type": "activity", 
            "name": "com.evernote.ui.TabManager"
        }, 
        {
            "filter": [], 
            "type": "activity", 
            "name": "com.evernote.ui.NotebookActivity"
        }, 
        {
            "filter": [], 
            "type": "activity", 
            "name": "com.evernote.ui.OfflineNotebookSettings"
        }, 
        {
            "filter": [], 
            "type": "activity", 
            "name": "com.evernote.ui.LinkedNotebookActivity"
        }, 
        {
            "filter": [], 
            "type": "activity", 
            "name": "com.evernote.ui.LinkedNotebookSettings"
        }, 
        {
            "filter": [], 
            "type": "activity", 
            "name": "com.evernote.ui.TagsActivity"
        }, 
        {
            "filter": [], 
            "type": "activity", 
            "name": "com.evernote.ui.InformationActivity"
        }, 
        {
            "filter": [
                {
                    "data": [], 
                    "categories": [
                        "android.intent.category.DEFAULT"
                    ], 
                    "actions": [
                        "com.evernote.action.VIEW_NOTELIST", 
                        "com.evernote.action.SEARCH_NOTES", 
                        "android.intent.action.SEARCH"
                    ]
                }, 
                {
                    "data": [], 
                    "categories": [
                        "android.intent.category.DEFAULT"
                    ], 
                    "actions": [
                        "com.evernote.action.VIEW_NOTELIST", 
                        "com.evernote.action.SEARCH_NOTES", 
                        "android.intent.action.SEARCH"
                    ]
                }, 
                {
                    "data": [], 
                    "categories": [
                        "android.intent.category.DEFAULT"
                    ], 
                    "actions": [
                        "com.evernote.action.VIEW_NOTELIST", 
                        "com.evernote.action.SEARCH_NOTES", 
                        "android.intent.action.SEARCH"
                    ]
                }
            ], 
            "type": "activity", 
            "name": "com.evernote.ui.NoteListActivity"
        }, 
        {
            "filter": [
                {
                    "data": [], 
                    "categories": [
                        "android.intent.category.DEFAULT"
                    ], 
                    "actions": [
                        "com.evernote.intent.action.VIEW", 
                        "com.evernote.action.VIEW_NOTELIST_TABLET"
                    ]
                }, 
                {
                    "data": [], 
                    "categories": [
                        "android.intent.category.DEFAULT"
                    ], 
                    "actions": [
                        "com.evernote.intent.action.VIEW", 
                        "com.evernote.action.VIEW_NOTELIST_TABLET"
                    ]
                }
            ], 
            "type": "activity", 
            "name": "com.evernote.ui.NoteListAloneActivity"
        }, 
        {
            "filter": [
                {
                    "data": [], 
                    "categories": [
                        "android.intent.category.DEFAULT"
                    ], 
                    "actions": [
                        "com.evernote.action.VIEW_NOTE"
                    ]
                }
            ], 
            "type": "activity", 
            "name": "com.evernote.ui.NoteViewActivity"
        }, 
        {
            "filter": [
                {
                    "data": [
                        {
                            "mimeType": null, 
                            "host": null, 
                            "scheme": "evernote"
                        }
                    ], 
                    "categories": [
                        "android.intent.category.BROWSABLE", 
                        "android.intent.category.DEFAULT"
                    ], 
                    "actions": [
                        "com.evernote.action.VIEW_NOTE_TABLET", 
                        "android.intent.action.VIEW"
                    ]
                }, 
                {
                    "data": [
                        {
                            "mimeType": null, 
                            "host": null, 
                            "scheme": "evernote"
                        }
                    ], 
                    "categories": [
                        "android.intent.category.BROWSABLE", 
                        "android.intent.category.DEFAULT"
                    ], 
                    "actions": [
                        "com.evernote.action.VIEW_NOTE_TABLET", 
                        "android.intent.action.VIEW"
                    ]
                }
            ], 
            "type": "activity", 
            "name": "com.evernote.ui.NoteViewAloneActivity"
        }, 
        {
            "filter": [], 
            "type": "activity", 
            "name": "com.evernote.ui.EvernotePreferenceActivity"
        }, 
        {
            "filter": [
                {
                    "data": [
                        {
                            "mimeType": "*/*", 
                            "host": null, 
                            "scheme": null
                        }
                    ], 
                    "categories": [
                        "android.intent.category.DEFAULT"
                    ], 
                    "actions": [
                        "com.evernote.action.NEW_VOICE_NOTE", 
                        "com.evernote.action.NEW_SKITCH_NOTE", 
                        "android.intent.action.SEND_MULTIPLE", 
                        "com.evernote.action.NEW_SNAPSHOT", 
                        "android.intent.action.SEND", 
                        "com.evernote.action.CREATE_NEW_NOTE"
                    ]
                }, 
                {
                    "data": [
                        {
                            "mimeType": "*/*", 
                            "host": null, 
                            "scheme": null
                        }
                    ], 
                    "categories": [
                        "android.intent.category.DEFAULT"
                    ], 
                    "actions": [
                        "com.evernote.action.NEW_VOICE_NOTE", 
                        "com.evernote.action.NEW_SKITCH_NOTE", 
                        "android.intent.action.SEND_MULTIPLE", 
                        "com.evernote.action.NEW_SNAPSHOT", 
                        "android.intent.action.SEND", 
                        "com.evernote.action.CREATE_NEW_NOTE"
                    ]
                }
            ], 
            "type": "activity", 
            "name": "com.evernote.ui.NewNoteActivity"
        }, 
        {
            "filter": [], 
            "type": "activity", 
            "name": "com.evernote.ui.NewNoteAloneActivity"
        }, 
        {
            "filter": [
                {
                    "data": [], 
                    "categories": [
                        "android.intent.category.DEFAULT"
                    ], 
                    "actions": [
                        "com.evernote.widget.action.NEW_SNAPSHOT", 
                        "com.evernote.widget.action.CREATE_NEW_NOTE", 
                        "com.evernote.widget.action.NEW_VOICE_NOTE", 
                        "com.evernote.widget.action.NEW_SKITCH_NOTE"
                    ]
                }
            ], 
            "type": "activity", 
            "name": "com.evernote.ui.WidgetNewNoteActivity"
        }, 
        {
            "filter": [], 
            "type": "activity", 
            "name": "com.evernote.ui.LearnMoreActivity"
        }, 
        {
            "filter": [], 
            "type": "activity", 
            "name": "com.evernote.ui.EmailActivity"
        }, 
        {
            "filter": [], 
            "type": "activity", 
            "name": "com.evernote.ui.TagEditActivity"
        }, 
        {
            "filter": [], 
            "type": "activity", 
            "name": "com.evernote.ui.NoteInfoActivity"
        }, 
        {
            "filter": [], 
            "type": "activity", 
            "name": "com.evernote.ui.FilePickerActivity"
        }, 
        {
            "filter": [], 
            "type": "activity", 
            "name": "com.evernote.ui.AuthenticationActivity"
        }, 
        {
            "filter": [], 
            "type": "activity", 
            "name": "com.evernote.ui.WebActivity"
        }, 
        {
            "filter": [], 
            "type": "activity", 
            "name": "com.evernote.ui.TrunkActivity"
        }, 
        {
            "filter": [], 
            "type": "activity", 
            "name": "com.evernote.ui.SearchActivity"
        }, 
        {
            "filter": [
                {
                    "data": [], 
                    "categories": [
                        "android.intent.category.DEFAULT"
                    ], 
                    "actions": [
                        "com.evernote.action.SEARCH"
                    ]
                }
            ], 
            "type": "activity", 
            "name": "com.evernote.ui.WidgetSearchActivity"
        }, 
        {
            "filter": [], 
            "type": "activity", 
            "name": "com.evernote.ui.AdvanceSearchActivity"
        }, 
        {
            "filter": [], 
            "type": "activity", 
            "name": "com.evernote.ui.AdvanceSearchSelector"
        }, 
        {
            "filter": [], 
            "type": "activity", 
            "name": "com.evernote.ui.LoginActivity"
        }, 
        {
            "filter": [], 
            "type": "activity", 
            "name": "com.evernote.ui.RegistrationActivity"
        }, 
        {
            "filter": [], 
            "type": "activity", 
            "name": "com.evernote.ui.CaptchaActivity"
        }, 
        {
            "filter": [], 
            "type": "activity", 
            "name": "com.evernote.ui.ResetPasswordActivity"
        }, 
        {
            "filter": [], 
            "type": "activity", 
            "name": "com.evernote.ui.RateAppActivity"
        }, 
        {
            "filter": [], 
            "type": "activity", 
            "name": "com.evernote.ui.DYNDialogActivity"
        }, 
        {
            "filter": [], 
            "type": "activity", 
            "name": "com.evernote.ui.StandardDialogActivity"
        }, 
        {
            "filter": [], 
            "type": "activity", 
            "name": "com.evernote.ui.ShareWithFacebook"
        }, 
        {
            "filter": [], 
            "type": "activity", 
            "name": "com.evernote.ui.ShareDialogActivity"
        }, 
        {
            "filter": [], 
            "type": "activity", 
            "name": "com.evernote.ui.SDCardChangedActivity"
        }, 
        {
            "filter": [
                {
                    "data": [
                        {
                            "mimeType": null, 
                            "host": "evernote.com", 
                            "scheme": "https"
                        }, 
                        {
                            "mimeType": null, 
                            "host": "www.evernote.com", 
                            "scheme": "https"
                        }, 
                        {
                            "mimeType": null, 
                            "host": "stage.evernote.com", 
                            "scheme": "https"
                        }, 
                        {
                            "mimeType": null, 
                            "host": "www.stage.evernote.com", 
                            "scheme": "https"
                        }
                    ], 
                    "categories": [
                        "android.intent.category.BROWSABLE", 
                        "android.intent.category.DEFAULT"
                    ], 
                    "actions": [
                        "android.intent.action.VIEW"
                    ]
                }
            ], 
            "type": "activity", 
            "name": "com.evernote.ui.helper.URIBrokerActivity"
        }, 
        {
            "filter": [], 
            "type": "activity", 
            "name": "com.evernote.billing.BillingActivity"
        }, 
        {
            "filter": [
                {
                    "data": [
                        {
                            "mimeType": null, 
                            "host": "evernote.com", 
                            "scheme": "https"
                        }, 
                        {
                            "mimeType": null, 
                            "host": "www.evernote.com", 
                            "scheme": "https"
                        }, 
                        {
                            "mimeType": null, 
                            "host": "stage.evernote.com", 
                            "scheme": "https"
                        }, 
                        {
                            "mimeType": null, 
                            "host": "www.stage.evernote.com", 
                            "scheme": "https"
                        }
                    ], 
                    "categories": [
                        "android.intent.category.BROWSABLE", 
                        "android.intent.category.DEFAULT"
                    ], 
                    "actions": [
                        "android.intent.action.VIEW"
                    ]
                }
            ], 
            "type": "activity", 
            "name": "com.evernote.billing.LaunchBillingActivity"
        }, 
        {
            "filter": [], 
            "type": "activity", 
            "name": "com.evernote.ui.NotebookShareSettingsActivity"
        }, 
        {
            "filter": [], 
            "type": "activity", 
            "name": "ui.EmailPickerActivity"
        }, 
        {
            "filter": [], 
            "type": "service", 
            "name": "com.evernote.client.EvernoteService"
        }, 
        {
            "filter": [], 
            "type": "service", 
            "name": "com.evernote.ui.helper.WidgetProviderService"
        }, 
        {
            "filter": [], 
            "type": "service", 
            "name": "com.evernote.client.SyncService"
        }, 
        {
            "filter": [], 
            "type": "service", 
            "name": "com.evernote.billing.BillingService"
        }, 
        {
            "filter": [
                {
                    "data": [], 
                    "categories": [], 
                    "actions": [
                        "android.appwidget.action.APPWIDGET_UPDATE"
                    ]
                }
            ], 
            "type": "receiver", 
            "name": "com.evernote.ui.EvernoteWidgetProvider"
        }, 
        {
            "filter": [
                {
                    "data": [], 
                    "categories": [], 
                    "actions": [
                        "android.appwidget.action.APPWIDGET_UPDATE"
                    ]
                }
            ], 
            "type": "receiver", 
            "name": "com.evernote.ui.EvernoteWidgetWSnippetProvider"
        }, 
        {
            "filter": [
                {
                    "data": [], 
                    "categories": [], 
                    "actions": [
                        "com.evernote.action.ACTION_RECENT_NOTES_CHANGED", 
                        "com.evernote.action.NOTE_UPLOADED", 
                        "com.evernote.action.THUMBNAIL_DONE", 
                        "com.evernote.action.CHUNK_DONE", 
                        "com.evernote.action.CONTENT_DONE", 
                        "com.evernote.action.SYNC_DONE", 
                        "com.evernote.action.ACTION_PINLOCK_STATE_CHANGE", 
                        "com.evernote.action.ACTION_PIN_SHOW_WIDGET_CHANGED", 
                        "com.evernote.action.LOGOUT_DONE", 
                        "com.evernote.action.SAVE_NOTE_DONE"
                    ]
                }, 
                {
                    "data": [], 
                    "categories": [], 
                    "actions": [
                        "com.evernote.action.ACTION_RECENT_NOTES_CHANGED", 
                        "com.evernote.action.NOTE_UPLOADED", 
                        "com.evernote.action.THUMBNAIL_DONE", 
                        "com.evernote.action.CHUNK_DONE", 
                        "com.evernote.action.CONTENT_DONE", 
                        "com.evernote.action.SYNC_DONE", 
                        "com.evernote.action.ACTION_PINLOCK_STATE_CHANGE", 
                        "com.evernote.action.ACTION_PIN_SHOW_WIDGET_CHANGED", 
                        "com.evernote.action.LOGOUT_DONE", 
                        "com.evernote.action.SAVE_NOTE_DONE"
                    ]
                }
            ], 
            "type": "receiver", 
            "name": "com.evernote.ui.helper.WidgetUpdateReceiver"
        }, 
        {
            "filter": [
                {
                    "data": [], 
                    "categories": [], 
                    "actions": [
                        "android.intent.action.BOOT_COMPLETED"
                    ]
                }
            ], 
            "type": "receiver", 
            "name": "com.evernote.BootReceiver"
        }, 
        {
            "filter": [
                {
                    "data": [], 
                    "categories": [], 
                    "actions": [
                        "com.evernote.action.SDCARD_CHANGED", 
                        "com.evernote.action.SYNC_ERROR", 
                        "com.evernote.action.DB_OPEN_CREATION_FAILED", 
                        "com.evernote.action.SYNC_DONE", 
                        "com.evernote.action.DB_CORRUPTED", 
                        "com.evernote.action.SYNC_STARTED", 
                        "com.evernote.action.DB_READ_ONLY", 
                        "com.evernote.action.SAVE_NOTE_DONE"
                    ]
                }
            ], 
            "type": "receiver", 
            "name": "com.evernote.ui.helper.SyncNotification"
        }, 
        {
            "filter": [
                {
                    "data": [], 
                    "categories": [], 
                    "actions": [
                        "com.sonyericsson.extras.livekey"
                    ]
                }
            ], 
            "type": "receiver", 
            "name": "com.evernote.ui.helper.LiveKeyAudioNoteReceiver"
        }, 
        {
            "filter": [
                {
                    "data": [], 
                    "categories": [], 
                    "actions": [
                        "com.evernote.ACTION_STOP_AUDIO_NOTE"
                    ]
                }
            ], 
            "type": "receiver", 
            "name": "com.evernote.ui.helper.StopAudioNoteReceiver"
        }, 
        {
            "filter": [
                {
                    "data": [], 
                    "categories": [], 
                    "actions": [
                        "com.android.vending.billing.IN_APP_NOTIFY", 
                        "com.android.vending.billing.PURCHASE_STATE_CHANGED", 
                        "com.android.vending.billing.RESPONSE_CODE"
                    ]
                }
            ], 
            "type": "receiver", 
            "name": "com.evernote.billing.BillingReceiver"
        }, 
        {
            "filter": [
                {
                    "data": [
                        {
                            "mimeType": null, 
                            "host": null, 
                            "scheme": "notificationId"
                        }
                    ], 
                    "categories": [], 
                    "actions": [
                        "com.evernote.action.ACTION_DELAYED_NOTIFICATION"
                    ]
                }
            ], 
            "type": "receiver", 
            "name": "com.evernote.util.MultiUseReceiver"
        }, 
        {
            "filter": [], 
            "type": "provider", 
            "name": "com.evernote.provider.EvernoteProvider"
        }
    ], 
    "name": "Evernote"
}